{
	"configurations" : 
	[
		{
			"directories" : 
			[
				{
					"build" : ".",
					"jsonFile" : "directory-.-Debug-d0094a50bb2071803777.json",
					"minimumCMakeVersion" : 
					{
						"string" : "3.6.0"
					},
					"projectIndex" : 0,
					"source" : ".",
					"targetIndexes" : 
					[
						0
					]
				}
			],
			"name" : "Debug",
			"projects" : 
			[
				{
					"directoryIndexes" : 
					[
						0
					],
					"name" : "isaivazhi_native",
					"targetIndexes" : 
					[
						0
					]
				}
			],
			"targets" : 
			[
				{
					"directoryIndex" : 0,
					"id" : "isaivazhi_native::@6890427a1f51a3e7e1df",
					"jsonFile" : "target-isaivazhi_native-Debug-9bf70600a1b54fae6327.json",
					"name" : "isaivazhi_native",
					"projectIndex" : 0
				}
			]
		}
	],
	"kind" : "codemodel",
	"paths" : 
	{
		"build" : "C:/Users/myuva/Documents/music_app_development/native/app/.cxx/Debug/2e3s5l23/x86",
		"source" : "C:/Users/myuva/Documents/music_app_development/native/app/src/main/cpp"
	},
	"version" : 
	{
		"major" : 2,
		"minor" : 3
	}
}
